fipy/.DS_Store
fipy/__init__.py
fipy/__init__.py~
fipy/_version.py
fipy/testFiPy.py
fipy/boundaryConditions/__init__.py
fipy/boundaryConditions/boundaryCondition.py
fipy/boundaryConditions/constraint.py
fipy/boundaryConditions/fixedFlux.py
fipy/boundaryConditions/fixedValue.py
fipy/boundaryConditions/nthOrderBoundaryCondition.py
fipy/boundaryConditions/test.py
fipy/matrices/__init__.py
fipy/matrices/offsetSparseMatrix.py
fipy/matrices/petscMatrix.py
fipy/matrices/scipyMatrix.py
fipy/matrices/sparseMatrix.py
fipy/matrices/test.py
fipy/matrices/trilinosMatrix.py
fipy/meshes/.DS_Store
fipy/meshes/__init__.py
fipy/meshes/abstractMesh.py
fipy/meshes/cylindricalGrid1D.py
fipy/meshes/cylindricalGrid2D.py
fipy/meshes/cylindricalNonUniformGrid1D.py
fipy/meshes/cylindricalNonUniformGrid2D.py
fipy/meshes/cylindricalUniformGrid1D.py
fipy/meshes/cylindricalUniformGrid2D.py
fipy/meshes/factoryMeshes.py
fipy/meshes/gmshMesh.py
fipy/meshes/grid1D.py
fipy/meshes/grid2D.py
fipy/meshes/grid3D.py
fipy/meshes/mesh.py
fipy/meshes/mesh1D.py
fipy/meshes/mesh2D.py
fipy/meshes/nonUniformGrid1D.py
fipy/meshes/nonUniformGrid2D.py
fipy/meshes/nonUniformGrid3D.py
fipy/meshes/periodicGrid1D.py
fipy/meshes/periodicGrid2D.py
fipy/meshes/periodicGrid3D.py
fipy/meshes/skewedGrid2D.py
fipy/meshes/sphericalNonUniformGrid1D.py
fipy/meshes/sphericalUniformGrid1D.py
fipy/meshes/test.py
fipy/meshes/tri2D.py
fipy/meshes/uniformGrid.py
fipy/meshes/uniformGrid1D.py
fipy/meshes/uniformGrid2D.py
fipy/meshes/uniformGrid3D.py
fipy/meshes/builders/__init__.py
fipy/meshes/builders/abstractGridBuilder.py
fipy/meshes/builders/grid1DBuilder.py
fipy/meshes/builders/grid2DBuilder.py
fipy/meshes/builders/grid3DBuilder.py
fipy/meshes/builders/periodicGrid1DBuilder.py
fipy/meshes/builders/utilityClasses.py
fipy/meshes/representations/__init__.py
fipy/meshes/representations/abstractRepresentation.py
fipy/meshes/representations/gridRepresentation.py
fipy/meshes/representations/meshRepresentation.py
fipy-4.0.1.dist-info/licenses/LICENSE.rst
fipy-4.0.1.dist-info/METADATA
fipy-4.0.1.dist-info/WHEEL
fipy-4.0.1.dist-info/entry_points.txt
fipy-4.0.1.dist-info/top_level.txt
fipy-4.0.1.dist-info/RECORD
