Metadata-Version: 2.4
Name: FiPy
Version: 4.0.1
Summary: A finite volume PDE solver in Python
Author: Jonathan Guyer, Daniel Wheeler, Jim Warren
Project-URL: Homepage, https://github.com/usnistgov/fipy
Project-URL: Issues, https://github.com/usnistgov/fipy/issues
Classifier: Development Status :: 5 - Production/Stable
Classifier: Environment :: Console
Classifier: Environment :: X11 Applications
Classifier: Intended Audience :: Science/Research
Classifier: Natural Language :: English
Classifier: Operating System :: OS Independent
Classifier: Programming Language :: Python
Classifier: Topic :: Scientific/Engineering :: Mathematics
Classifier: Topic :: Scientific/Engineering :: Physics
Classifier: Topic :: Scientific/Engineering :: Visualization
Classifier: Topic :: Software Development :: Libraries :: Python Modules
Requires-Python: >=3.7
License-File: LICENSE.rst
Requires-Dist: numpy
Requires-Dist: scipy
Requires-Dist: matplotlib
Requires-Dist: typer
Dynamic: license-file
